{
  "lighting": "qmk_rgblight",
  "matrix": {
    "rows": 12,
    "cols": 11
  },
  "customKeycodes": [
    {
      "name": "KB sleep",
      "title": "Keyboard sleep",
      "shortName": "SLEEP"
    },
    {
      "name": "Trackball mode",
      "title": "Trackball mode",
      "shortname": "TB_CYCLE"
    }
  ],
  "layouts": {
    "keymap": [
      [
        "0,0",
        {
          "x": 1
        },
        "0,2",
        "0,3",
        "0,4",
        "0,5",
        {
          "x": 0.5
        },
        "0,6",
        "0,7",
        "0,8",
        "0,9",
        {
          "x": 0.5
        },
        "6,0",
        "6,1",
        "6,2",
        "6,3",
        {
          "x": 0.25
        },
        "6,4",
        "6,5",
        "6,6"
      ],
      [
        {
          "y": 0.5
        },
        "1,0",
        "1,1",
        "1,2",
        "1,3",
        "1,4",
        "1,5",
        "1,6",
        "1,7",
        "1,8",
        "1,9",
        "7,0",
        "7,1",
        "7,2",
        {
          "w": 2
        },
        "7,3",
        {
          "x": 0.25
        },
        "7,4",
        "7,5",
        "7,6",
        {
          "x": 0.25
        },
        "7,7",
        "7,8",
        "7,9",
        "7,10"
      ],
      [
        {
          "w": 1.5
        },
        "2,0",
        "2,1",
        "2,2",
        "2,3",
        "2,4",
        "2,5",
        "2,6",
        "2,7",
        "2,8",
        "2,9",
        "8,0",
        "8,1",
        "8,2",
        {
          "w": 1.5
        },
        "8,3",
        {
          "x": 0.25
        },
        "8,4",
        "8,5",
        "8,6",
        {
          "x": 0.25
        },
        "8,7",
        "8,8",
        "8,9",
        {
          "h": 2
        },
        "8,10"
      ],
      [
        {
          "w": 1.75
        },
        "3,0",
        "3,1",
        "3,3",
        "3,4",
        "3,5",
        "3,6",
        "3,7",
        "3,8",
        "3,9",
        "9,0",
        "9,1",
        "9,2",
        {
          "w": 2.25
        },
        "9,3",
        {
          "x": 3.5
        },
        "9,7",
        "9,8",
        "9,9"
      ],
      [
        {
          "w": 2.25
        },
        "4,0",
        "4,2",
        "4,3",
        "4,4",
        "4,5",
        "4,6",
        "4,7",
        "4,8",
        "4,9",
        "10,0",
        "10,1",
        {
          "w": 2.75
        },
        "10,3",
        {
          "x": 1.25
        },
        "10,5",
        {
          "x": 1.25
        },
        "10,7",
        "10,8",
        "10,9",
        {
          "h": 2
        },
        "10,10"
      ],
      [
        {
          "w": 1.25
        },
        "5,0",
        {
          "w": 1.25
        },
        "5,1",
        {
          "w": 1.25
        },
        "5,2",
        {
          "w": 6.25
        },
        "5,6",
        {
          "w": 1.25
        },
        "11,0",
        {
          "w": 1.25
        },
        "11,1",
        {
          "w": 1.25
        },
        "11,2",
        {
          "w": 1.25
        },
        "11,3",
        {
          "x": 0.25
        },
        "11,4",
        "11,5",
        "11,6",
        {
          "x": 0.25,
          "w": 2
        },
        "11,7",
        "11,9"
      ]
    ]
  }
}
